primerserver2/__init__.py
primerserver2/cmd/__init__.py
primerserver2/cmd/isoforms.py
primerserver2/cmd/junctions.py
primerserver2/cmd/primertool.py
primerserver2/core/Santalucia_NN_Tm.py
primerserver2/core/__init__.py
primerserver2/core/analysis_blast.py
primerserver2/core/design_primer.py
primerserver2/core/global_var.py
primerserver2/core/make_primers.py
primerserver2/core/make_sites.py
primerserver2/core/multiplex.py
primerserver2/core/output.py
primerserver2/core/qRT.py
primerserver2/core/run_blast.py
primerserver2/core/sort_primers.py
primerserver2/core/version.py
primerserver2/data/p3_settings.json
primerserver2/data/web_config_sample.json
primerserver2/web/__init__.py
primerserver2/web/config.py
primerserver2/web/db.py
primerserver2/web/download.py
primerserver2/web/run.py
primerserver2/web/static/favicon.ico
primerserver2/web/static/css/back-to-top.css
primerserver2/web/static/css/bootstrap-select.min.css
primerserver2/web/static/css/bootstrap.min.css
primerserver2/web/static/css/font-awesome.min.css
primerserver2/web/static/css/gh-fork-ribbon.ie.min.css
primerserver2/web/static/css/gh-fork-ribbon.min.css
primerserver2/web/static/css/style.css
primerserver2/web/static/css/validationEngine.jquery.css
primerserver2/web/static/fonts/FontAwesome.otf
primerserver2/web/static/fonts/fontawesome-webfont.eot
primerserver2/web/static/fonts/fontawesome-webfont.svg
primerserver2/web/static/fonts/fontawesome-webfont.ttf
primerserver2/web/static/fonts/fontawesome-webfont.woff
primerserver2/web/static/fonts/fontawesome-webfont.woff2
primerserver2/web/static/fonts/glyphicons-halflings-regular.eot
primerserver2/web/static/fonts/glyphicons-halflings-regular.svg
primerserver2/web/static/fonts/glyphicons-halflings-regular.ttf
primerserver2/web/static/fonts/glyphicons-halflings-regular.woff
primerserver2/web/static/fonts/glyphicons-halflings-regular.woff2
primerserver2/web/static/js/FileSaver.min.js
primerserver2/web/static/js/back-to-top.js
primerserver2-2.0.0b20.dist-info/LICENSE
primerserver2-2.0.0b20.dist-info/METADATA
primerserver2-2.0.0b20.dist-info/WHEEL
primerserver2-2.0.0b20.dist-info/entry_points.txt
primerserver2-2.0.0b20.dist-info/top_level.txt
primerserver2-2.0.0b20.dist-info/RECORD
