Metadata-Version: 2.1
Name: primerserver2
Version: 2.0.0b20
Summary: a high-throughput primer design and specificity-checking platform
Home-page: https://github.com/billzt/PrimerServer2
Author: Tao Zhu
Author-email: taozhu@mail.bnu.edu.cn
License: MIT
Keywords: primer bioinformatics PCR
Platform: UNKNOWN
Classifier: Development Status :: 4 - Beta
Classifier: Environment :: Console
Classifier: Intended Audience :: Science/Research
Classifier: License :: OSI Approved :: MIT License
Classifier: Operating System :: Unix
Classifier: Programming Language :: Python :: 3.6
Classifier: Topic :: Scientific/Engineering :: Bio-Informatics
Requires-Python: >=3.6, <3.9
License-File: LICENSE
Requires-Dist: primer3-py (<0.7)
Requires-Dist: progressbar2 (<3.56)
Requires-Dist: flask (<2.1)
Requires-Dist: python-dotenv (<0.20)
Requires-Dist: python-utils (<2.7)
Requires-Dist: six (<1.17)
